{
  "topRated": [
    {
      "name": "Kyoto Hotel 1",
      "city": "Kyoto",
      "address": "Kyoto 중심가 10번지",
      "rating": "4.4",
      "lowestPrice": 147392,
      "image": "https://picsum.photos/seed/Kyoto-0/400/250",
      "amenities": "Family, WiFi"
    },
    {
      "name": "Kyoto Hotel 2",
      "city": "Kyoto",
      "address": "Kyoto 중심가 11번지",
      "rating": "4.1",
      "lowestPrice": 79509,
      "image": "https://picsum.photos/seed/Kyoto-1/400/250",
      "amenities": "Pet Friendly, Pool"
    },
    {
      "name": "Kyoto Hotel 3",
      "city": "Kyoto",
      "address": "Kyoto 중심가 12번지",
      "rating": "4.2",
      "lowestPrice": 135465,
      "image": "https://picsum.photos/seed/Kyoto-2/400/250",
      "amenities": "Family, WiFi"
    },
    {
      "name": "Kyoto Hotel 4",
      "city": "Kyoto",
      "address": "Kyoto 중심가 13번지",
      "rating": "4.0",
      "lowestPrice": 131259,
      "image": "https://picsum.photos/seed/Kyoto-3/400/250",
      "amenities": "Pet Friendly, Pool"
    },
    {
      "name": "Kyoto Hotel 5",
      "city": "Kyoto",
      "address": "Kyoto 중심가 14번지",
      "rating": "4.5",
      "lowestPrice": 160619,
      "image": "https://picsum.photos/seed/Kyoto-4/400/250",
      "amenities": "Family, WiFi"
    }
  ],
  "petFriendly": [
    {
      "name": "Kyoto Hotel 2",
      "city": "Kyoto",
      "address": "Kyoto 중심가 11번지",
      "rating": "4.1",
      "lowestPrice": 79509,
      "image": "https://picsum.photos/seed/Kyoto-1/400/250",
      "amenities": "Pet Friendly, Pool"
    },
    {
      "name": "Kyoto Hotel 4",
      "city": "Kyoto",
      "address": "Kyoto 중심가 13번지",
      "rating": "4.0",
      "lowestPrice": 131259,
      "image": "https://picsum.photos/seed/Kyoto-3/400/250",
      "amenities": "Pet Friendly, Pool"
    },
    {
      "name": "Kyoto Hotel 6",
      "city": "Kyoto",
      "address": "Kyoto 중심가 15번지",
      "rating": "4.5",
      "lowestPrice": 155812,
      "image": "https://picsum.photos/seed/Kyoto-5/400/250",
      "amenities": "Pet Friendly, Pool"
    },
    {
      "name": "Kyoto Hotel 8",
      "city": "Kyoto",
      "address": "Kyoto 중심가 17번지",
      "rating": "4.9",
      "lowestPrice": 118541,
      "image": "https://picsum.photos/seed/Kyoto-7/400/250",
      "amenities": "Pet Friendly, Pool"
    },
    {
      "name": "Kyoto Hotel 10",
      "city": "Kyoto",
      "address": "Kyoto 중심가 19번지",
      "rating": "4.0",
      "lowestPrice": 104180,
      "image": "https://picsum.photos/seed/Kyoto-9/400/250",
      "amenities": "Pet Friendly, Pool"
    }
  ],
  "family": [
    {
      "name": "Kyoto Hotel 1",
      "city": "Kyoto",
      "address": "Kyoto 중심가 10번지",
      "rating": "4.4",
      "lowestPrice": 147392,
      "image": "https://picsum.photos/seed/Kyoto-0/400/250",
      "amenities": "Family, WiFi"
    },
    {
      "name": "Kyoto Hotel 3",
      "city": "Kyoto",
      "address": "Kyoto 중심가 12번지",
      "rating": "4.2",
      "lowestPrice": 135465,
      "image": "https://picsum.photos/seed/Kyoto-2/400/250",
      "amenities": "Family, WiFi"
    },
    {
      "name": "Kyoto Hotel 5",
      "city": "Kyoto",
      "address": "Kyoto 중심가 14번지",
      "rating": "4.5",
      "lowestPrice": 160619,
      "image": "https://picsum.photos/seed/Kyoto-4/400/250",
      "amenities": "Family, WiFi"
    },
    {
      "name": "Kyoto Hotel 7",
      "city": "Kyoto",
      "address": "Kyoto 중심가 16번지",
      "rating": "4.6",
      "lowestPrice": 75078,
      "image": "https://picsum.photos/seed/Kyoto-6/400/250",
      "amenities": "Family, WiFi"
    },
    {
      "name": "Kyoto Hotel 9",
      "city": "Kyoto",
      "address": "Kyoto 중심가 18번지",
      "rating": "4.1",
      "lowestPrice": 73276,
      "image": "https://picsum.photos/seed/Kyoto-8/400/250",
      "amenities": "Family, WiFi"
    }
  ]
}